[
  {
    "name": "Node.js",
    "htmlURL": "https://github.com/nodejs/node",
    "description": "Javascript runtime",
    "languages": [
      "C++", "Javascript", "C"
    ]
  },
  {
    "name": "Jarvis",
    "htmlURL": "https://github.com/sukeesh/Jarvis",
    "description": "Rule based personal assistant for linux and macOS",
    "languages": [ "Python" ]
  },
  {
    "name": "BadgeYay",
    "htmlURL": "https://github.com/fossasia/badgeyay",
    "description": "Badge generator service with awesome customization features",
    "languages": [ "Python", "Javascript" ]
  },
  {
    "name": "Parsy",
    "htmlURL": "https://github.com/yashLadha/Parsy",
    "description": "Goto OCR messenger chatbot for extracting text from images",
    "languages": [ "Python" ]
  },
  {
    "name": "go-moji",
    "htmlURL": "https://github.com/yashLadha/go-moji",
    "description": "Emojify your git commits",
    "languages": [ "go" ]
  },
  {
    "name": "10-fast-fingers-hack",
    "htmlURL": "https://github.com/yashLadha/10-fast-fingers-hack",
    "description": "Automated play on 10-fast-fingers",
    "languages": [ "Python" ]
  },
  {
    "name": "clean-dependa",
    "htmlURL": "https://github.com/yashLadha/clean-dependa",
    "description": "Close your dependabot PRs in lazy way",
    "languages": [ "Rust" ]
  },
  {
    "name": "sqsPeek",
    "htmlURL": "https://github.com/yashLadha/sqsPeek",
    "description": "Peek messages in your sqs elegantly",
    "languages": ["Go"]
  }
]